setup.cfg
setup.py
MathAndPhysics/MathAndPhysics.py
MathAndPhysics.egg-info/PKG-INFO
MathAndPhysics.egg-info/SOURCES.txt
MathAndPhysics.egg-info/dependency_links.txt
MathAndPhysics.egg-info/not-zip-safe
MathAndPhysics.egg-info/top_level.txt