Metadata-Version: 2.1
Name: MathAndPhysics
Version: 0.0
Summary: Math and physics library
Home-page: UNKNOWN
Author-email: xudaverdiyevxudaverdi1983@gmail.com
License: UNKNOWN
Platform: UNKNOWN
